LICENSE
MANIFEST.in
README.md
requirements.txt
setup.cfg
setup.py
delivery/__init__.py
delivery/admin.py
delivery/fields.py
delivery/forms.py
delivery/lib.py
delivery/models.py
delivery/routers.py
delivery/translation.py
delivery/urls.py
delivery/views.py
delivery/widgets.py
delivery/locale/ru/LC_MESSAGES/django.mo
delivery/locale/ru/LC_MESSAGES/django.po
delivery/locale/uk/LC_MESSAGES/django.mo
delivery/locale/uk/LC_MESSAGES/django.po
delivery/migrations/0001_initial.py
delivery/migrations/__init__.py
delivery/static/delivery.css
delivery/static/delivery.js
delivery/static/jquery.autocomplete.min.js
delivery/templates/delivery/form.html
delivery/templates/delivery/media.html
django_mp_delivery.egg-info/PKG-INFO
django_mp_delivery.egg-info/SOURCES.txt
django_mp_delivery.egg-info/dependency_links.txt
django_mp_delivery.egg-info/top_level.txt