Metadata-Version: 2.1
Name: django-mp-delivery
Version: 1.0.2
Summary: Django delivery app
Home-page: https://github.com/pmaigutyak/mp-delivery
Author: Paul Maigutyak
Author-email: pmaigutyak@gmail.com
License: MIT
Download-URL: https://github.com/pmaigutyak/mp-delivery/archive/1.0.2.tar.gz
Platform: UNKNOWN
License-File: LICENSE
